Metadata-Version: 2.1
Name: visualiser
Version: 0.9
Summary: A terminal visualiser.
Home-page: https://github.com/probablyhamzah/visualiser
Author: possiblyhamzah
Author-email: possiblyhamzah@gmail.com
License: MIT
Download-URL: https://github.com/probablyhamzah/visualiser/archive/v_09.tar.gz
Keywords: visualiser,terminal
Platform: UNKNOWN
Classifier: Development Status :: 3 - Alpha
Classifier: Intended Audience :: Developers
Classifier: Topic :: Software Development :: Build Tools
Classifier: License :: OSI Approved :: MIT License
Classifier: Programming Language :: Python :: 3
Classifier: Programming Language :: Python :: 3.4
Classifier: Programming Language :: Python :: 3.5
Classifier: Programming Language :: Python :: 3.6
Classifier: Programming Language :: Python :: 3.7
Classifier: Programming Language :: Python :: 3.8
